{
    "symbol": "507753",
    "quarterly": [
        {
            "date": "2025-06-30",
            "quarterLabel": "Q1 FY26",
            "annualLabel": "FY26",
            "revenue": 4909400000.0,
            "earnings": 387500000.0,
            "ebitda": 993000000.0,
            "profitMargin": 7.893021550494969,
            "revenueYoY": null,
            "earningsYoY": null
        },
        {
            "date": "2025-09-30",
            "quarterLabel": "Q2 FY26",
            "annualLabel": "FY26",
            "revenue": 4999400000.0,
            "earnings": 370500000.0,
            "ebitda": 962000000.0,
            "profitMargin": 7.410889306716806,
            "revenueYoY": null,
            "earningsYoY": null
        },
        {
            "date": "2025-12-31",
            "quarterLabel": "Q3 FY26",
            "annualLabel": "FY26",
            "revenue": 4482500000.0,
            "earnings": 281000000.0,
            "ebitda": 836300000.0,
            "profitMargin": 6.268823201338539,
            "revenueYoY": null,
            "earningsYoY": null
        },
        {
            "date": "2026-03-31",
            "quarterLabel": "Q4 FY26",
            "annualLabel": "FY26",
            "revenue": 5111100000.0,
            "earnings": 279900000.0,
            "ebitda": 870300000.0,
            "profitMargin": 5.4763162528614195,
            "revenueYoY": 4.987367253456032,
            "earningsYoY": 28.986175115207374
        }
    ],
    "annual": [
        {
            "date": "2023-03-31",
            "quarterLabel": "Q4 FY23",
            "annualLabel": "FY23",
            "revenue": 23162433000.0,
            "earnings": 3616246000.0,
            "ebitda": 5417523000.0,
            "profitMargin": 15.612548129119249,
            "revenueYoY": null,
            "earningsYoY": null
        },
        {
            "date": "2024-03-31",
            "quarterLabel": "Q4 FY24",
            "annualLabel": "FY24",
            "revenue": 15346222000.0,
            "earnings": 607210000.0,
            "ebitda": 1890145000.0,
            "profitMargin": 3.956739319944674,
            "revenueYoY": -33.74520716368613,
            "earningsYoY": -83.20883037271247
        },
        {
            "date": "2025-03-31",
            "quarterLabel": "Q4 FY25",
            "annualLabel": "FY25",
            "revenue": 17490400000.0,
            "earnings": 921200000.0,
            "ebitda": 2391700000.0,
            "profitMargin": 5.266889264968211,
            "revenueYoY": 13.972025166845626,
            "earningsYoY": 51.71028145122774
        },
        {
            "date": "2026-03-31",
            "quarterLabel": "Q4 FY26",
            "annualLabel": "FY26",
            "revenue": 19502400000.0,
            "earnings": 1318900000.0,
            "ebitda": 3661600000.0,
            "profitMargin": 6.7627574042169165,
            "revenueYoY": 11.503453322965742,
            "earningsYoY": 43.171949630916195
        }
    ]
}