{
    "symbol": "512065",
    "quarterly": [
        {
            "date": "2025-06-30",
            "quarterLabel": "Q1 FY26",
            "annualLabel": "FY26",
            "revenue": 0.0,
            "earnings": -478000.0,
            "ebitda": -478000.0,
            "profitMargin": null,
            "revenueYoY": null,
            "earningsYoY": null
        },
        {
            "date": "2025-09-30",
            "quarterLabel": "Q2 FY26",
            "annualLabel": "FY26",
            "revenue": 9825000.0,
            "earnings": -291000.0,
            "ebitda": -290000.0,
            "profitMargin": -2.9618320610687023,
            "revenueYoY": null,
            "earningsYoY": null
        },
        {
            "date": "2025-12-31",
            "quarterLabel": "Q3 FY26",
            "annualLabel": "FY26",
            "revenue": 38445000.0,
            "earnings": 2613000.0,
            "ebitda": 3485000.0,
            "profitMargin": 6.7967225907140065,
            "revenueYoY": null,
            "earningsYoY": null
        },
        {
            "date": "2026-03-31",
            "quarterLabel": "Q4 FY26",
            "annualLabel": "FY26",
            "revenue": 65067000.0,
            "earnings": -5049000.0,
            "ebitda": -5014000.0,
            "profitMargin": -7.759693854027387,
            "revenueYoY": -16.350196053223627,
            "earningsYoY": -65.27004909983634
        }
    ],
    "annual": [
        {
            "date": "2023-03-31",
            "quarterLabel": "Q4 FY23",
            "annualLabel": "FY23",
            "revenue": 0.0,
            "earnings": -85000.0,
            "ebitda": -85000.0,
            "profitMargin": null,
            "revenueYoY": null,
            "earningsYoY": null
        },
        {
            "date": "2024-03-31",
            "quarterLabel": "Q4 FY24",
            "annualLabel": "FY24",
            "revenue": 0.0,
            "earnings": -166000.0,
            "ebitda": -150000.0,
            "profitMargin": null,
            "revenueYoY": null,
            "earningsYoY": -95.29411764705881
        },
        {
            "date": "2025-03-31",
            "quarterLabel": "Q4 FY25",
            "annualLabel": "FY25",
            "revenue": 202429000.0,
            "earnings": 3460000.0,
            "ebitda": 4086000.0,
            "profitMargin": 1.709241264838536,
            "revenueYoY": null,
            "earningsYoY": 2184.3373493975905
        },
        {
            "date": "2026-03-31",
            "quarterLabel": "Q4 FY26",
            "annualLabel": "FY26",
            "revenue": 113337000.0,
            "earnings": -2351000.0,
            "ebitda": -2314000.0,
            "profitMargin": -2.074344653555326,
            "revenueYoY": -44.01148056849562,
            "earningsYoY": -167.9479768786127
        }
    ]
}