{
    "symbol": "513511",
    "quarterly": [
        {
            "date": "2025-03-31",
            "quarterLabel": "Q4 FY25",
            "annualLabel": "FY25",
            "revenue": 912083000.0,
            "earnings": -20293000.0,
            "ebitda": 6545000.0,
            "profitMargin": -2.2249071630542394,
            "revenueYoY": null,
            "earningsYoY": null
        },
        {
            "date": "2025-06-30",
            "quarterLabel": "Q1 FY26",
            "annualLabel": "FY26",
            "revenue": 875404000.0,
            "earnings": -19246000.0,
            "ebitda": 8415000.0,
            "profitMargin": -2.198527765466002,
            "revenueYoY": null,
            "earningsYoY": null
        },
        {
            "date": "2025-12-31",
            "quarterLabel": "Q3 FY26",
            "annualLabel": "FY26",
            "revenue": 981057000.0,
            "earnings": 12253000.0,
            "ebitda": 50799000.0,
            "profitMargin": 1.24895903092277,
            "revenueYoY": 3.573445775958632,
            "earningsYoY": -26.24894667148188
        },
        {
            "date": "2026-03-31",
            "quarterLabel": "Q4 FY26",
            "annualLabel": "FY26",
            "revenue": 1059630000.0,
            "earnings": -21188000.0,
            "ebitda": 42880000.0,
            "profitMargin": -1.9995658862055625,
            "revenueYoY": 16.17692688055802,
            "earningsYoY": -4.410387818459567
        }
    ],
    "annual": [
        {
            "date": "2023-03-31",
            "quarterLabel": "Q4 FY23",
            "annualLabel": "FY23",
            "revenue": 4871244000.0,
            "earnings": 13783000.0,
            "ebitda": 156418000.0,
            "profitMargin": 0.2829462042960689,
            "revenueYoY": null,
            "earningsYoY": null
        },
        {
            "date": "2024-03-31",
            "quarterLabel": "Q4 FY24",
            "annualLabel": "FY24",
            "revenue": 4266541000.0,
            "earnings": 29692000.0,
            "ebitda": 189798000.0,
            "profitMargin": 0.6959267472174766,
            "revenueYoY": -12.413728402847404,
            "earningsYoY": 115.42479866502214
        },
        {
            "date": "2025-03-31",
            "quarterLabel": "Q4 FY25",
            "annualLabel": "FY25",
            "revenue": 3831011000.0,
            "earnings": 33253000.0,
            "ebitda": 182210000.0,
            "profitMargin": 0.8679954194858746,
            "revenueYoY": -10.208035033531846,
            "earningsYoY": 11.993129462481477
        },
        {
            "date": "2026-03-31",
            "quarterLabel": "Q4 FY26",
            "annualLabel": "FY26",
            "revenue": 3842412000.0,
            "earnings": -22634000.0,
            "ebitda": 141290000.0,
            "profitMargin": -0.5890570818537939,
            "revenueYoY": 0.2975976837445781,
            "earningsYoY": -168.066039154362
        }
    ]
}