{
    "symbol": "531540",
    "quarterly": [
        {
            "date": "2025-06-30",
            "quarterLabel": "Q1 FY26",
            "annualLabel": "FY26",
            "revenue": 170972000.0,
            "earnings": 2787000.0,
            "ebitda": 5377000.0,
            "profitMargin": 1.6300914769669888,
            "revenueYoY": null,
            "earningsYoY": null
        },
        {
            "date": "2025-09-30",
            "quarterLabel": "Q2 FY26",
            "annualLabel": "FY26",
            "revenue": 127358000.0,
            "earnings": 2408000.0,
            "ebitda": 5307000.0,
            "profitMargin": 1.8907332087501374,
            "revenueYoY": null,
            "earningsYoY": null
        },
        {
            "date": "2025-12-31",
            "quarterLabel": "Q3 FY26",
            "annualLabel": "FY26",
            "revenue": 123480000.0,
            "earnings": 2560000.0,
            "ebitda": 5576000.0,
            "profitMargin": 2.0732102364755427,
            "revenueYoY": null,
            "earningsYoY": null
        },
        {
            "date": "2026-03-31",
            "quarterLabel": "Q4 FY26",
            "annualLabel": "FY26",
            "revenue": 143047000.0,
            "earnings": 4184000.0,
            "ebitda": 17627000.0,
            "profitMargin": 2.9249127909008927,
            "revenueYoY": -36.54454395840819,
            "earningsYoY": -76.71286247008405
        }
    ],
    "annual": [
        {
            "date": "2023-03-31",
            "quarterLabel": "Q4 FY23",
            "annualLabel": "FY23",
            "revenue": 351833000.0,
            "earnings": 10135000.0,
            "ebitda": 26033000.0,
            "profitMargin": 2.880628025227878,
            "revenueYoY": null,
            "earningsYoY": null
        },
        {
            "date": "2024-03-31",
            "quarterLabel": "Q4 FY24",
            "annualLabel": "FY24",
            "revenue": 383967000.0,
            "earnings": 16895000.0,
            "ebitda": 38678000.0,
            "profitMargin": 4.400117718449763,
            "revenueYoY": 9.13331040578911,
            "earningsYoY": 66.69955599407992
        },
        {
            "date": "2025-03-31",
            "quarterLabel": "Q4 FY25",
            "annualLabel": "FY25",
            "revenue": 507333000.0,
            "earnings": 19288000.0,
            "ebitda": 38256000.0,
            "profitMargin": 3.801842182550711,
            "revenueYoY": 32.129323613748056,
            "earningsYoY": 14.16395383249482
        },
        {
            "date": "2026-03-31",
            "quarterLabel": "Q4 FY26",
            "annualLabel": "FY26",
            "revenue": 564856000.0,
            "earnings": 11936000.0,
            "ebitda": 34069000.0,
            "profitMargin": 2.1131049329386604,
            "revenueYoY": 11.338312311637525,
            "earningsYoY": -38.11696391538781
        }
    ]
}