{
    "symbol": "531744",
    "quarterly": [
        {
            "date": "2025-06-30",
            "quarterLabel": "Q1 FY26",
            "annualLabel": "FY26",
            "revenue": 91383000.0,
            "earnings": 1385000.0,
            "ebitda": 10464000.0,
            "profitMargin": 1.5155991814670124,
            "revenueYoY": null,
            "earningsYoY": null
        },
        {
            "date": "2025-09-30",
            "quarterLabel": "Q2 FY26",
            "annualLabel": "FY26",
            "revenue": 107486000.0,
            "earnings": 9982000.0,
            "ebitda": 12311000.0,
            "profitMargin": 9.286790837876561,
            "revenueYoY": null,
            "earningsYoY": null
        },
        {
            "date": "2025-12-31",
            "quarterLabel": "Q3 FY26",
            "annualLabel": "FY26",
            "revenue": 89113000.0,
            "earnings": 2203000.0,
            "ebitda": 8445000.0,
            "profitMargin": 2.472142111700874,
            "revenueYoY": null,
            "earningsYoY": null
        },
        {
            "date": "2026-03-31",
            "quarterLabel": "Q4 FY26",
            "annualLabel": "FY26",
            "revenue": 102451000.0,
            "earnings": 2286000.0,
            "ebitda": 5220000.0,
            "profitMargin": 2.231310577739602,
            "revenueYoY": -7.092462275101568,
            "earningsYoY": -30.76923076923077
        }
    ],
    "annual": [
        {
            "date": "2023-03-31",
            "quarterLabel": "Q4 FY23",
            "annualLabel": "FY23",
            "revenue": 461838000.0,
            "earnings": 15306000.0,
            "ebitda": 39324000.0,
            "profitMargin": 3.3141491172229225,
            "revenueYoY": null,
            "earningsYoY": null
        },
        {
            "date": "2024-03-31",
            "quarterLabel": "Q4 FY24",
            "annualLabel": "FY24",
            "revenue": 437262000.0,
            "earnings": 30356000.0,
            "ebitda": 56230000.0,
            "profitMargin": 6.942290891959511,
            "revenueYoY": -5.321346446156444,
            "earningsYoY": 98.32745328629295
        },
        {
            "date": "2025-03-31",
            "quarterLabel": "Q4 FY25",
            "annualLabel": "FY25",
            "revenue": 400265000.0,
            "earnings": 18042000.0,
            "ebitda": 41082000.0,
            "profitMargin": 4.507513772125966,
            "revenueYoY": -8.461059959475097,
            "earningsYoY": -40.565291869811574
        },
        {
            "date": "2026-03-31",
            "quarterLabel": "Q4 FY26",
            "annualLabel": "FY26",
            "revenue": 390433000.0,
            "earnings": 15858000.0,
            "ebitda": 36443000.0,
            "profitMargin": 4.061644379445386,
            "revenueYoY": -2.4563726531173096,
            "earningsYoY": -12.105088127702029
        }
    ]
}