{
    "symbol": "535910",
    "quarterly": [
        {
            "date": "2025-06-30",
            "quarterLabel": "Q1 FY26",
            "annualLabel": "FY26",
            "revenue": 3201000.0,
            "earnings": 1118000.0,
            "ebitda": 1133000.0,
            "profitMargin": 34.92658544204936,
            "revenueYoY": null,
            "earningsYoY": null
        },
        {
            "date": "2025-09-30",
            "quarterLabel": "Q2 FY26",
            "annualLabel": "FY26",
            "revenue": 2255000.0,
            "earnings": -474000.0,
            "ebitda": -461000.0,
            "profitMargin": -21.019955654101995,
            "revenueYoY": null,
            "earningsYoY": null
        },
        {
            "date": "2025-12-31",
            "quarterLabel": "Q3 FY26",
            "annualLabel": "FY26",
            "revenue": 8704000.0,
            "earnings": 4002000.0,
            "ebitda": 4030000.0,
            "profitMargin": 45.978860294117645,
            "revenueYoY": null,
            "earningsYoY": null
        },
        {
            "date": "2026-03-31",
            "quarterLabel": "Q4 FY26",
            "annualLabel": "FY26",
            "revenue": 4174000.0,
            "earnings": 1289000.0,
            "ebitda": 1303000.0,
            "profitMargin": 30.88164829899377,
            "revenueYoY": -27.383437717466947,
            "earningsYoY": -38.67745004757374
        }
    ],
    "annual": [
        {
            "date": "2023-03-31",
            "quarterLabel": "Q4 FY23",
            "annualLabel": "FY23",
            "revenue": 22449000.0,
            "earnings": 4888000.0,
            "ebitda": 15237000.0,
            "profitMargin": 21.77379838745601,
            "revenueYoY": null,
            "earningsYoY": null
        },
        {
            "date": "2024-03-31",
            "quarterLabel": "Q4 FY24",
            "annualLabel": "FY24",
            "revenue": 20673000.0,
            "earnings": 5085000.0,
            "ebitda": 13541000.0,
            "profitMargin": 24.597300827165867,
            "revenueYoY": -7.91126553521315,
            "earningsYoY": 4.030278232405892
        },
        {
            "date": "2025-03-31",
            "quarterLabel": "Q4 FY25",
            "annualLabel": "FY25",
            "revenue": 21413000.0,
            "earnings": 5119000.0,
            "ebitda": 6988000.0,
            "profitMargin": 23.906038387895205,
            "revenueYoY": 3.579548202970058,
            "earningsYoY": 0.6686332350049163
        },
        {
            "date": "2026-03-31",
            "quarterLabel": "Q4 FY26",
            "annualLabel": "FY26",
            "revenue": 15133000.0,
            "earnings": 3567000.0,
            "ebitda": 4822000.0,
            "profitMargin": 23.57100376660279,
            "revenueYoY": -29.327978330920466,
            "earningsYoY": -30.31842156671225
        }
    ]
}