{
    "symbol": "542628",
    "quarterly": [
        {
            "date": "2025-06-30",
            "quarterLabel": "Q1 FY26",
            "annualLabel": "FY26",
            "revenue": 5341248000.0,
            "earnings": 73802000.0,
            "ebitda": 138567000.0,
            "profitMargin": 1.3817370022886037,
            "revenueYoY": null,
            "earningsYoY": null
        },
        {
            "date": "2025-09-30",
            "quarterLabel": "Q2 FY26",
            "annualLabel": "FY26",
            "revenue": 5626807000.0,
            "earnings": 75902000.0,
            "ebitda": 140577000.0,
            "profitMargin": 1.3489355508372687,
            "revenueYoY": null,
            "earningsYoY": null
        },
        {
            "date": "2025-12-31",
            "quarterLabel": "Q3 FY26",
            "annualLabel": "FY26",
            "revenue": 5962441000.0,
            "earnings": 71820000.0,
            "ebitda": 128315000.0,
            "profitMargin": 1.204540221026925,
            "revenueYoY": null,
            "earningsYoY": null
        },
        {
            "date": "2026-03-31",
            "quarterLabel": "Q4 FY26",
            "annualLabel": "FY26",
            "revenue": 6159239000.0,
            "earnings": 49779000.0,
            "ebitda": 110763000.0,
            "profitMargin": 0.8082004935999398,
            "revenueYoY": 32.03625271688508,
            "earningsYoY": 138.01759586879604
        }
    ],
    "annual": [
        {
            "date": "2023-03-31",
            "quarterLabel": "Q4 FY23",
            "annualLabel": "FY23",
            "revenue": 9053410000.0,
            "earnings": 111337000.0,
            "ebitda": 223654000.0,
            "profitMargin": 1.2297797183602643,
            "revenueYoY": null,
            "earningsYoY": null
        },
        {
            "date": "2024-03-31",
            "quarterLabel": "Q4 FY24",
            "annualLabel": "FY24",
            "revenue": 12353058000.0,
            "earnings": 165728000.0,
            "ebitda": 312016000.0,
            "profitMargin": 1.3415949313926965,
            "revenueYoY": 36.44646602771773,
            "earningsYoY": 48.85258269937218
        },
        {
            "date": "2025-03-31",
            "quarterLabel": "Q4 FY25",
            "annualLabel": "FY25",
            "revenue": 19426138000.0,
            "earnings": 229696000.0,
            "ebitda": 473164000.0,
            "profitMargin": 1.1824069199961413,
            "revenueYoY": 57.25772517218004,
            "earningsYoY": 38.59818497779494
        },
        {
            "date": "2026-03-31",
            "quarterLabel": "Q4 FY26",
            "annualLabel": "FY26",
            "revenue": 23089735000.0,
            "earnings": 271420000.0,
            "ebitda": 518341000.0,
            "profitMargin": 1.1755007149280838,
            "revenueYoY": 18.859111368404776,
            "earningsYoY": 18.164878796322096
        }
    ]
}