{
    "symbol": "AIRAN",
    "quarterly": [
        {
            "date": "2025-06-30",
            "quarterLabel": "Q1 FY26",
            "annualLabel": "FY26",
            "revenue": 256989000.0,
            "earnings": 31507000.0,
            "ebitda": 55093000.0,
            "profitMargin": 12.260057823486608,
            "revenueYoY": null,
            "earningsYoY": null
        },
        {
            "date": "2025-09-30",
            "quarterLabel": "Q2 FY26",
            "annualLabel": "FY26",
            "revenue": 262698000.0,
            "earnings": 7523000.0,
            "ebitda": 24073000.0,
            "profitMargin": 2.863744680203123,
            "revenueYoY": null,
            "earningsYoY": null
        },
        {
            "date": "2025-12-31",
            "quarterLabel": "Q3 FY26",
            "annualLabel": "FY26",
            "revenue": 292980000.0,
            "earnings": 77414000.0,
            "ebitda": 109597000.0,
            "profitMargin": 26.42296402484811,
            "revenueYoY": null,
            "earningsYoY": null
        },
        {
            "date": "2026-03-31",
            "quarterLabel": "Q4 FY26",
            "annualLabel": "FY26",
            "revenue": 309707000.0,
            "earnings": 4709000.0,
            "ebitda": 26112000.0,
            "profitMargin": 1.520469346834266,
            "revenueYoY": 13.388470297065952,
            "earningsYoY": 113.64690198806005
        }
    ],
    "annual": [
        {
            "date": "2023-03-31",
            "quarterLabel": "Q4 FY23",
            "annualLabel": "FY23",
            "revenue": 973853000.0,
            "earnings": 103586000.0,
            "ebitda": 195762000.0,
            "profitMargin": 10.636718272675651,
            "revenueYoY": null,
            "earningsYoY": null
        },
        {
            "date": "2024-03-31",
            "quarterLabel": "Q4 FY24",
            "annualLabel": "FY24",
            "revenue": 1054966000.0,
            "earnings": 125466000.0,
            "ebitda": 226361000.0,
            "profitMargin": 11.89289512647801,
            "revenueYoY": 8.329080466969861,
            "earningsYoY": 21.122545517734057
        },
        {
            "date": "2025-03-31",
            "quarterLabel": "Q4 FY25",
            "annualLabel": "FY25",
            "revenue": 1064984000.0,
            "earnings": 184756000.0,
            "ebitda": 292284000.0,
            "profitMargin": 17.348241851520775,
            "revenueYoY": 0.9496040630693311,
            "earningsYoY": 47.255830264772925
        },
        {
            "date": "2026-03-31",
            "quarterLabel": "Q4 FY26",
            "annualLabel": "FY26",
            "revenue": 1122374000.0,
            "earnings": 121153000.0,
            "ebitda": 214875000.0,
            "profitMargin": 10.794351971802625,
            "revenueYoY": 5.388813353064458,
            "earningsYoY": -34.425404317045185
        }
    ]
}