{
    "symbol": "ASAHIINDIA",
    "quarterly": [
        {
            "date": "2025-03-31",
            "quarterLabel": "Q4 FY25",
            "annualLabel": "FY25",
            "revenue": 11478000000.0,
            "earnings": 924100000.0,
            "ebitda": 2056800000.0,
            "profitMargin": 8.051054190625544,
            "revenueYoY": null,
            "earningsYoY": null
        },
        {
            "date": "2025-06-30",
            "quarterLabel": "Q1 FY26",
            "annualLabel": "FY26",
            "revenue": 12185800000.0,
            "earnings": 561700000.0,
            "ebitda": 2030400000.0,
            "profitMargin": 4.609463473879433,
            "revenueYoY": null,
            "earningsYoY": null
        },
        {
            "date": "2025-12-31",
            "quarterLabel": "Q3 FY26",
            "annualLabel": "FY26",
            "revenue": 12203600000.0,
            "earnings": 995000000.0,
            "ebitda": 2489900000.0,
            "profitMargin": 8.153331803730046,
            "revenueYoY": 8.444634018465695,
            "earningsYoY": -5.597722960151803
        },
        {
            "date": "2026-03-31",
            "quarterLabel": "Q4 FY26",
            "annualLabel": "FY26",
            "revenue": 13254700000.0,
            "earnings": 1324800000.0,
            "ebitda": 2962800000.0,
            "profitMargin": 9.994945189253624,
            "revenueYoY": 15.47917755706569,
            "earningsYoY": 43.36110810518342
        }
    ],
    "annual": [
        {
            "date": "2023-03-31",
            "quarterLabel": "Q4 FY23",
            "annualLabel": "FY23",
            "revenue": 39831900000.0,
            "earnings": 3648800000.0,
            "ebitda": 8237700000.0,
            "profitMargin": 9.160496988594568,
            "revenueYoY": null,
            "earningsYoY": null
        },
        {
            "date": "2024-03-31",
            "quarterLabel": "Q4 FY24",
            "annualLabel": "FY24",
            "revenue": 43060100000.0,
            "earnings": 3279800000.0,
            "ebitda": 7543100000.0,
            "profitMargin": 7.616796059461079,
            "revenueYoY": 8.10455941092441,
            "earningsYoY": -10.112913834685376
        },
        {
            "date": "2025-03-31",
            "quarterLabel": "Q4 FY25",
            "annualLabel": "FY25",
            "revenue": 45517400000.0,
            "earnings": 3712700000.0,
            "ebitda": 8346600000.0,
            "profitMargin": 8.156660969211774,
            "revenueYoY": 5.706675089003509,
            "earningsYoY": 13.198975547289468
        },
        {
            "date": "2026-03-31",
            "quarterLabel": "Q4 FY26",
            "annualLabel": "FY26",
            "revenue": 49060200000.0,
            "earnings": 3447000000.0,
            "ebitda": 9478800000.0,
            "profitMargin": 7.026061858696051,
            "revenueYoY": 7.783397118464587,
            "earningsYoY": -7.1565168206426595
        }
    ]
}