{
    "symbol": "BANKINDIA",
    "quarterly": [
        {
            "date": "2025-03-31",
            "quarterLabel": "Q4 FY25",
            "annualLabel": "FY25",
            "revenue": 96009300000.0,
            "earnings": 26019800000.0,
            "ebitda": null,
            "profitMargin": 27.10133289170945,
            "revenueYoY": null,
            "earningsYoY": null
        },
        {
            "date": "2025-06-30",
            "quarterLabel": "Q1 FY26",
            "annualLabel": "FY26",
            "revenue": 83567900000.0,
            "earnings": 18295600000.0,
            "ebitda": null,
            "profitMargin": 21.893095315306475,
            "revenueYoY": null,
            "earningsYoY": null
        },
        {
            "date": "2025-12-31",
            "quarterLabel": "Q3 FY26",
            "annualLabel": "FY26",
            "revenue": 88749700000.0,
            "earnings": 28122900000.0,
            "ebitda": null,
            "profitMargin": 31.68788176185384,
            "revenueYoY": 11.889726156061165,
            "earningsYoY": 6.659460689498236
        },
        {
            "date": "2026-03-31",
            "quarterLabel": "Q4 FY26",
            "annualLabel": "FY26",
            "revenue": 100683000000.0,
            "earnings": 30877600000.0,
            "ebitda": null,
            "profitMargin": 30.668136626838695,
            "revenueYoY": 4.867965915801907,
            "earningsYoY": 18.669628513670357
        }
    ],
    "annual": [
        {
            "date": "2023-03-31",
            "quarterLabel": "Q4 FY23",
            "annualLabel": "FY23",
            "revenue": 263604079000.0,
            "earnings": 38379536000.0,
            "ebitda": null,
            "profitMargin": 14.559537980442252,
            "revenueYoY": null,
            "earningsYoY": null
        },
        {
            "date": "2024-03-31",
            "quarterLabel": "Q4 FY24",
            "annualLabel": "FY24",
            "revenue": 294491053000.0,
            "earnings": 65644637000.0,
            "ebitda": null,
            "profitMargin": 22.29087652452382,
            "revenueYoY": 11.717183632807139,
            "earningsYoY": 71.04072597438385
        },
        {
            "date": "2025-03-31",
            "quarterLabel": "Q4 FY25",
            "annualLabel": "FY25",
            "revenue": 315318916000.0,
            "earnings": 95482800000.0,
            "ebitda": null,
            "profitMargin": 30.28134220783634,
            "revenueYoY": 7.072494321245134,
            "earningsYoY": 45.45407570766215
        },
        {
            "date": "2026-03-31",
            "quarterLabel": "Q4 FY26",
            "annualLabel": "FY26",
            "revenue": 325981955000.0,
            "earnings": 103062992000.0,
            "ebitda": null,
            "profitMargin": 31.616164765930066,
            "revenueYoY": 3.381668037955579,
            "earningsYoY": 7.938803637932695
        }
    ]
}