{
    "symbol": "KOTHARIPET",
    "quarterly": [
        {
            "date": "2025-06-30",
            "quarterLabel": "Q1 FY26",
            "annualLabel": "FY26",
            "revenue": 1606691000.0,
            "earnings": 175765000.0,
            "ebitda": 251176000.0,
            "profitMargin": 10.939564608253859,
            "revenueYoY": null,
            "earningsYoY": null
        },
        {
            "date": "2025-09-30",
            "quarterLabel": "Q2 FY26",
            "annualLabel": "FY26",
            "revenue": 1430246000.0,
            "earnings": 184156000.0,
            "ebitda": 268361000.0,
            "profitMargin": 12.875826955642596,
            "revenueYoY": null,
            "earningsYoY": null
        },
        {
            "date": "2025-12-31",
            "quarterLabel": "Q3 FY26",
            "annualLabel": "FY26",
            "revenue": 1348350000.0,
            "earnings": 186957000.0,
            "ebitda": 276969000.0,
            "profitMargin": 13.865613527644898,
            "revenueYoY": null,
            "earningsYoY": null
        },
        {
            "date": "2026-03-31",
            "quarterLabel": "Q4 FY26",
            "annualLabel": "FY26",
            "revenue": 1528580000.0,
            "earnings": 178023000.0,
            "ebitda": 263664000.0,
            "profitMargin": 11.646299179630768,
            "revenueYoY": -0.038779130942018986,
            "earningsYoY": 3.046422783051632
        }
    ],
    "annual": [
        {
            "date": "2023-03-31",
            "quarterLabel": "Q4 FY23",
            "annualLabel": "FY23",
            "revenue": 4790009000.0,
            "earnings": 391769000.0,
            "ebitda": 639435000.0,
            "profitMargin": 8.178878160771722,
            "revenueYoY": null,
            "earningsYoY": null
        },
        {
            "date": "2024-03-31",
            "quarterLabel": "Q4 FY24",
            "annualLabel": "FY24",
            "revenue": 5921631000.0,
            "earnings": 637841000.0,
            "ebitda": 1032663000.0,
            "profitMargin": 10.771373630001598,
            "revenueYoY": 23.624632020524388,
            "earningsYoY": 62.81048270792227
        },
        {
            "date": "2025-03-31",
            "quarterLabel": "Q4 FY25",
            "annualLabel": "FY25",
            "revenue": 5773394000.0,
            "earnings": 658178000.0,
            "ebitda": 917182000.0,
            "profitMargin": 11.4001919841258,
            "revenueYoY": -2.5033136985401487,
            "earningsYoY": 3.1884121591431094
        },
        {
            "date": "2026-03-31",
            "quarterLabel": "Q4 FY26",
            "annualLabel": "FY26",
            "revenue": 5913867000.0,
            "earnings": 724900000.0,
            "ebitda": 1060168000.0,
            "profitMargin": 12.257631089775947,
            "revenueYoY": 2.4331095366087956,
            "earningsYoY": 10.137379249990124
        }
    ]
}