{
    "symbol": "KUSUMGAR",
    "quarterly": [],
    "annual": [
        {
            "date": "2023-03-31",
            "quarterLabel": "Q4 FY23",
            "annualLabel": "FY23",
            "revenue": 2953520000.0,
            "earnings": 372170000.0,
            "ebitda": 688220000.0,
            "profitMargin": 12.600896557328205,
            "revenueYoY": null,
            "earningsYoY": null
        },
        {
            "date": "2024-03-31",
            "quarterLabel": "Q4 FY24",
            "annualLabel": "FY24",
            "revenue": 4556940000.0,
            "earnings": 843960000.0,
            "ebitda": 1362730000.0,
            "profitMargin": 18.5203228482271,
            "revenueYoY": 54.288442265500144,
            "earningsYoY": 126.76733750705323
        },
        {
            "date": "2025-03-31",
            "quarterLabel": "Q4 FY25",
            "annualLabel": "FY25",
            "revenue": 7700950000.0,
            "earnings": 1119880000.0,
            "ebitda": 1980950000.0,
            "profitMargin": 14.542101948460903,
            "revenueYoY": 68.99388624822798,
            "earningsYoY": 32.693492582586856
        },
        {
            "date": "2026-03-31",
            "quarterLabel": "Q4 FY26",
            "annualLabel": "FY26",
            "revenue": 6748140000.0,
            "earnings": 982000000.0,
            "ebitda": 2058780000.0,
            "profitMargin": 14.552158076151352,
            "revenueYoY": -12.372629350924237,
            "earningsYoY": -12.312033432153445
        }
    ]
}